pds/api_client/__init__.py
pds/api_client/api_client.py
pds/api_client/api_response.py
pds/api_client/configuration.py
pds/api_client/exceptions.py
pds/api_client/preprocess_openapi.py
pds/api_client/py.typed
pds/api_client/rest.py
pds/api_client/api/4_health_api.py
pds/api_client/api/__init__.py
pds/api_client/api/all_docs_api.py
pds/api_client/api/all_products_api.py
pds/api_client/api/by_product_classes_api.py
pds/api_client/api/deprecated_api.py
pds/api_client/api/health_api.py
pds/api_client/api/healthcheck_api.py
pds/api_client/api/product_references_api.py
pds/api_client/demo/__init__.py
pds/api_client/demo/client-demo.py
pds/api_client/demo/et_bundle_title.py
pds/api_client/demo/get_all_members.py
pds/api_client/demo/get_messenger_mdis_products.py
pds/api_client/models/__init__.py
pds/api_client/models/error_message.py
pds/api_client/models/facet_histogram.py
pds/api_client/models/facet_terms.py
pds/api_client/models/metadata.py
pds/api_client/models/pds4_metadata.py
pds/api_client/models/pds4_metadata_ops_data_file.py
pds/api_client/models/pds4_metadata_ops_label_file_info.py
pds/api_client/models/pds4_metadata_ops_tracking_meta.py
pds/api_client/models/pds4_product.py
pds/api_client/models/pds4_products.py
pds/api_client/models/pds_product.py
pds/api_client/models/pds_products.py
pds/api_client/models/properties_list_inner.py
pds/api_client/models/reference.py
pds/api_client/models/summary.py
pds/api_client/models/summary_facet.py
pds/api_client/models/wyriwyg_product.py
pds/api_client/models/wyriwyg_product_key_value_pair.py
pds/api_client/models/wyriwyg_products.py
pds/api_client/test/__init__.py
pds/api_client/test/integration/__init__.py
pds/api_client/test/integration/constants.py
pds/api_client/test/integration/test_collections.py
pds/api_client/test/integration/test_collections_of_bundle.py
pds/api_client/test/integration/test_pagination.py
pds/api_client/test/integration/test_products.py
pds_api_client-1.7.0.dist-info/licenses/LICENSE.txt
pds_api_client-1.7.0.dist-info/licenses/NOTICE.txt
pds_api_client-1.7.0.dist-info/METADATA
pds_api_client-1.7.0.dist-info/WHEEL
pds_api_client-1.7.0.dist-info/top_level.txt
pds_api_client-1.7.0.dist-info/RECORD
