Metadata-Version: 2.4
Name: pds.api-client
Version: 1.7.0
Summary: PDS Registry Search API
Home-page: 
Author: OpenAPI Generator community
Author-email: pds-operator@jpl.nasa.gov
License: Apache 2.0
Keywords: OpenAPI,OpenAPI-Generator,PDS Registry Search API
License-File: LICENSE.txt
License-File: NOTICE.txt
Requires-Dist: urllib3<3.0.0,>=1.25.3
Requires-Dist: python-dateutil>=2.8.2
Requires-Dist: pydantic>=2
Requires-Dist: typing-extensions>=4.7.1
Dynamic: author
Dynamic: author-email
Dynamic: description
Dynamic: description-content-type
Dynamic: keywords
Dynamic: license
Dynamic: license-file
Dynamic: requires-dist
Dynamic: summary
